coordio/__init__.py
coordio/astrometry.py
coordio/calibration.py
coordio/conv.py
coordio/coordinate.py
coordio/defaults.py
coordio/exceptions.py
coordio/extraction.py
coordio/fitData.py
coordio/guide.py
coordio/iers.py
coordio/libcoordio.cpython-313-x86_64-linux-gnu.so
coordio/libsofa.cpython-313-x86_64-linux-gnu.so
coordio/positioner.py
coordio/site.py
coordio/sky.py
coordio/sofa_bindings.py
coordio/tangent.py
coordio/telescope.py
coordio/time.py
coordio/transforms.py
coordio/utils.py
coordio/wok.py
coordio/zhaoburge.py
coordio/etc/astrometrynet.cfg
coordio/etc/coordio.yml
coordio/include/coordio.h
sdss_coordio-1.18.1.dist-info/METADATA
sdss_coordio-1.18.1.dist-info/WHEEL
sdss_coordio-1.18.1.dist-info/top_level.txt
sdss_coordio-1.18.1.dist-info/RECORD
sdss_coordio-1.18.1.dist-info/licenses/LICENSE.md
