Metadata-Version: 2.4
Name: sdss-coordio
Version: 1.18.1
Summary: Coordinate conversion for SDSS-V
Home-page: https://github.com/sdss/coordio
Author: Conor Sayres
Author-email: csayres@uw.edu
License: BSD 3-Clause License
Project-URL: Repository, https://github.com/sdss/coordio
Project-URL: Documentation, https://sdss-coordio.readthedocs.org
Keywords: astronomy,software,coordinates
Classifier: Intended Audience :: Science/Research
Classifier: Natural Language :: English
Classifier: Operating System :: OS Independent
Classifier: Programming Language :: Python
Classifier: Programming Language :: Python :: 3.7
Classifier: Programming Language :: Python :: 3.8
Classifier: Programming Language :: Python :: 3.9
Classifier: Topic :: Documentation :: Sphinx
Classifier: Topic :: Software Development :: Libraries :: Python Modules
Requires-Python: >=3.9
License-File: LICENSE.md
Requires-Dist: sdsstools>=1.0.0; python_version > "3.7"
Requires-Dist: sdsstools<1.0.0; python_version <= "3.7"
Requires-Dist: numpy<1.23.0; python_version <= "3.7"
Requires-Dist: numpy<2,>=1.23.0; python_version > "3.7"
Requires-Dist: pandas>=1.2.1
Requires-Dist: matplotlib>=3.1.1
Requires-Dist: scipy>=1.2.1
Requires-Dist: pybind11>=2.6.2
Requires-Dist: scikit-image>=0.17.2
Requires-Dist: sep>=1.4.1
Requires-Dist: astropy<5.0.0; python_version <= "3.7"
Requires-Dist: astropy>=5.0.0; python_version > "3.7"
Requires-Dist: seaborn>=0.12.1
Requires-Dist: pyarrow>=15.0.0; python_version > "3.7"
Provides-Extra: dev
Requires-Dist: flake8>=3.7.9; extra == "dev"
Requires-Dist: doc8>=0.8.0; extra == "dev"
Requires-Dist: pytest>=5.2.2; extra == "dev"
Requires-Dist: pytest-cov>=2.8.1; extra == "dev"
Requires-Dist: pytest-mock>=1.13.0; extra == "dev"
Requires-Dist: pytest-sugar>=0.9.2; extra == "dev"
Requires-Dist: isort>=4.3.21; extra == "dev"
Requires-Dist: coverage[toml]>=5.0; extra == "dev"
Requires-Dist: ipdb>=0.12.3; extra == "dev"
Requires-Dist: rstcheck>=3.3.1; extra == "dev"
Requires-Dist: twine>=3.4.2; extra == "dev"
Requires-Dist: wheel>=0.36.2; extra == "dev"
Requires-Dist: sphinx>=4.0; extra == "dev"
Dynamic: license-file
